reasoning_deployment_service/__init__.py
reasoning_deployment_service/reasoning_deployment_service.py
reasoning_deployment_service/runner.py
reasoning_deployment_service/cli_editor/__init__.py
reasoning_deployment_service/cli_editor/api_client.py
reasoning_deployment_service/cli_editor/cli_runner.py
reasoning_deployment_service/cli_editor/config.py
reasoning_deployment_service/cli_editor/google_deps.py
reasoning_deployment_service/gui_editor/__init__.py
reasoning_deployment_service/gui_editor/agent_checkbox_list.py
reasoning_deployment_service/gui_editor/main.py
reasoning_deployment_service/gui_editor/src/__init__.py
reasoning_deployment_service/gui_editor/src/core/__init__.py
reasoning_deployment_service/gui_editor/src/core/api_client.py
reasoning_deployment_service/gui_editor/src/core/config.py
reasoning_deployment_service/gui_editor/src/core/google_deps.py
reasoning_deployment_service/gui_editor/src/core/reasoning_engine_creator.py
reasoning_deployment_service/gui_editor/src/ui/__init__.py
reasoning_deployment_service/gui_editor/src/ui/agent_space_view.py
reasoning_deployment_service/gui_editor/src/ui/authorization_view.py
reasoning_deployment_service/gui_editor/src/ui/reasoning_engine_view.py
reasoning_deployment_service/gui_editor/src/ui/reasoning_engines_view.py
reasoning_deployment_service/gui_editor/src/ui/ui_components.py
reasoning_deployment_service-0.8.6.dist-info/METADATA
reasoning_deployment_service-0.8.6.dist-info/WHEEL
reasoning_deployment_service-0.8.6.dist-info/entry_points.txt
reasoning_deployment_service-0.8.6.dist-info/top_level.txt
reasoning_deployment_service-0.8.6.dist-info/RECORD
