Metadata-Version: 2.4
Name: reasoning-deployment-service
Version: 0.8.6
Summary: Deployment helper for Vertex AI Reasoning Engines & Agent Spaces
Author-email: Sergio Estrada <sergio.estrada@accenture.com>
License: Apache-2.0
Project-URL: Homepage, https://github.com/AxG-AI-Exchange-GenAI-Initiative/AIXAgentDeploymentService
Project-URL: Repository, https://github.com/AxG-AI-Exchange-GenAI-Initiative/AIXAgentDeploymentService
Project-URL: Issues, https://github.com/AxG-AI-Exchange-GenAI-Initiative/AIXAgentDeploymentService/issues
Requires-Python: >=3.9
Requires-Dist: requests>=2.28
Requires-Dist: python-dotenv>=1.0
Requires-Dist: google-auth>=2.20
Requires-Dist: google-cloud-storage>=2.16
Requires-Dist: google-cloud-aiplatform[adk,agent-engines]>=1.88.0
Requires-Dist: protobuf<7.0.0,>=4.21
Requires-Dist: keyring>=24.0
Requires-Dist: keyrings.google-artifactregistry-auth>=1.1
Requires-Dist: PyYAML>=6.0
Requires-Dist: click>=8.0
Provides-Extra: dev
Requires-Dist: pytest; extra == "dev"
Requires-Dist: build; extra == "dev"
Requires-Dist: twine; extra == "dev"
Requires-Dist: black; extra == "dev"
Requires-Dist: ruff; extra == "dev"
